Metadata-Version: 2.1
Name: ocotillo-speechify
Version: 1.0.5.2
Summary: A fork of a simple & fast speech transcription toolkit
Home-page: https://github.com/speechifyInc/ocotillo_speechify
Author: Tyler
Author-email: tyler@speechify.com
License: UNKNOWN
Platform: UNKNOWN
Classifier: Programming Language :: Python :: 3
Classifier: License :: OSI Approved :: Apache Software License
Classifier: Operating System :: OS Independent
Requires-Python: >=3.6
License-File: LICENSE.txt
